analyzefrc/__init__.py
analyzefrc/file_read.py
analyzefrc/helper.py
analyzefrc/plot.py
analyzefrc/process.py
analyzefrc/read.py
analyzefrc-0.2.3.dist-info/LICENSE
analyzefrc-0.2.3.dist-info/WHEEL
analyzefrc-0.2.3.dist-info/METADATA
analyzefrc-0.2.3.dist-info/RECORD
